pal/__init__.py
pal/cli/__init__.py
pal/cli/main.py
pal/core/__init__.py
pal/core/compiler.py
pal/core/evaluation.py
pal/core/executor.py
pal/core/loader.py
pal/core/resolver.py
pal/exceptions/__init__.py
pal/exceptions/core.py
pal/models/__init__.py
pal/models/schema.py
pal_framework-0.0.4.dist-info/METADATA
pal_framework-0.0.4.dist-info/WHEEL
pal_framework-0.0.4.dist-info/entry_points.txt
pal_framework-0.0.4.dist-info/licenses/LICENSE
pal_framework-0.0.4.dist-info/RECORD
