Metadata-Version: 2.4
Name: pal-framework
Version: 0.0.4
Summary: Prompt Assembly Language - A framework for managing LLM prompts as versioned, composable software artifacts
Project-URL: Homepage, https://github.com/cyqlelabs/pal
Project-URL: Documentation, https://pal-framework.readthedocs.io
Project-URL: Repository, https://github.com/cyqlelabs/pal
Project-URL: Issues, https://github.com/cyqlelabs/pal/issues
Author-email: Nicolas Iglesias <nfiglesias@gmail.com>
License: MIT License
License-File: LICENSE
Keywords: ai,claude,gpt,llm,prompt-engineering,prompts
Classifier: Development Status :: 3 - Alpha
Classifier: Intended Audience :: Developers
Classifier: License :: OSI Approved :: MIT License
Classifier: Programming Language :: Python :: 3
Classifier: Programming Language :: Python :: 3.12
Classifier: Topic :: Scientific/Engineering :: Artificial Intelligence
Classifier: Topic :: Software Development :: Libraries :: Python Modules
Requires-Python: >=3.12
Requires-Dist: click>=8.1.7
Requires-Dist: httpx>=0.27.0
Requires-Dist: importlib-metadata>=8.7.0
Requires-Dist: jinja2>=3.1.4
Requires-Dist: pydantic>=2.8.0
Requires-Dist: pyyaml>=6.0.1
Requires-Dist: rich>=13.7.0
Requires-Dist: ruff>=0.12.8
Requires-Dist: structlog>=24.2.0
Provides-Extra: all
Requires-Dist: anthropic>=0.18.0; extra == 'all'
Requires-Dist: openai>=1.0.0; extra == 'all'
Provides-Extra: anthropic
Requires-Dist: anthropic>=0.18.0; extra == 'anthropic'
Provides-Extra: dev
Requires-Dist: mypy>=1.11.0; extra == 'dev'
Requires-Dist: pre-commit>=3.7.0; extra == 'dev'
Requires-Dist: pytest-asyncio>=0.23.0; extra == 'dev'
Requires-Dist: pytest-cov>=5.0.0; extra == 'dev'
Requires-Dist: pytest>=8.3.0; extra == 'dev'
Requires-Dist: ruff>=0.5.0; extra == 'dev'
Provides-Extra: docs
Requires-Dist: doc8>=1.1.0; extra == 'docs'
Requires-Dist: myst-parser>=4.0.0; extra == 'docs'
Requires-Dist: sphinx-autoapi>=3.3.0; extra == 'docs'
Requires-Dist: sphinx-autobuild>=2024.10.0; extra == 'docs'
Requires-Dist: sphinx-autodoc-typehints>=2.5.0; extra == 'docs'
Requires-Dist: sphinx-copybutton>=0.5.2; extra == 'docs'
Requires-Dist: sphinx-rtd-theme>=3.0.2; extra == 'docs'
Requires-Dist: sphinx>=8.1.0; extra == 'docs'
Provides-Extra: openai
Requires-Dist: openai>=1.0.0; extra == 'openai'
Provides-Extra: test
Requires-Dist: pytest-asyncio>=0.23.0; extra == 'test'
Requires-Dist: pytest-cov>=5.0.0; extra == 'test'
Requires-Dist: pytest>=8.3.0; extra == 'test'
